_bbfreeze_loader/__init__.py
_bbfreeze_loader/console.exe
refrigerant_loader-1.1.0.dist-info/METADATA
refrigerant_loader-1.1.0.dist-info/WHEEL
refrigerant_loader-1.1.0.dist-info/top_level.txt
refrigerant_loader-1.1.0.dist-info/RECORD
